{"commitInfo":{"timestamp":1776726276717,"operation":"WRITE","operationParameters":{"mode":"Append"},"engineInfo":"delta-rs:py-1.5.0","clientVersion":"delta-rs.py-1.5.0","operationMetrics":{"execution_time_ms":2,"num_added_files":1,"num_added_rows":2,"num_partitions":0,"num_removed_files":0}}}
{"protocol":{"minReaderVersion":1,"minWriterVersion":2}}
{"metaData":{"id":"e4d6946b-c80b-472d-84e4-96b7075a2891","name":null,"description":null,"format":{"provider":"parquet","options":{}},"schemaString":"{\"type\":\"struct\",\"fields\":[{\"name\":\"match_id\",\"type\":\"string\",\"nullable\":true,\"metadata\":{}},{\"name\":\"raw_json\",\"type\":\"string\",\"nullable\":true,\"metadata\":{}},{\"name\":\"ingested_at\",\"type\":\"timestamp\",\"nullable\":true,\"metadata\":{}},{\"name\":\"endpoint\",\"type\":\"string\",\"nullable\":true,\"metadata\":{}},{\"name\":\"status_code\",\"type\":\"long\",\"nullable\":true,\"metadata\":{}},{\"name\":\"region\",\"type\":\"string\",\"nullable\":true,\"metadata\":{}}]}","partitionColumns":[],"createdTime":1776726276714,"configuration":{}}}
{"add":{"path":"part-00000-bb93f4d4-f86b-421d-8d8c-e192358efd6e-c000.snappy.parquet","partitionValues":{},"size":6052,"modificationTime":1776726276717,"dataChange":true,"stats":"{\"numRecords\":2,\"minValues\":{\"match_id\":\"BR1_GOLD001\",\"status_code\":200,\"region\":\"americas\",\"raw_json\":\"{\\\"metadata\\\": {\\\"dataVersion\\\": \\\"2\\\", \\\"matchId\\\": \\\"BR1_GOLD001\\\", \\\"par\",\"ingested_at\":\"2026-04-20T23:04:36.697730Z\",\"endpoint\":\"/lol/match/v5/matches\"},\"maxValues\":{\"region\":\"americas\",\"raw_json\":\"{\\\"metadata\\\": {\\\"dataVersion\\\": \\\"2\\\", \\\"matchId\\\": \\\"BR1_GOLD002\\\", \\\"pas\",\"match_id\":\"BR1_GOLD002\",\"status_code\":200,\"ingested_at\":\"2026-04-20T23:04:36.697730Z\",\"endpoint\":\"/lol/match/v5/matches\"},\"nullCount\":{\"endpoint\":0,\"region\":0,\"raw_json\":0,\"ingested_at\":0,\"match_id\":0,\"status_code\":0}}","tags":null,"baseRowId":null,"defaultRowCommitVersion":null,"clusteringProvider":null}}