{"commitInfo":{"timestamp":1776709776492,"operation":"MERGE","operationParameters":{"mergePredicate":"t.match_id = s.match_id AND t.frame_index = s.frame_index AND t.participant_id = s.participant_id","notMatchedPredicates":"[{\"actionType\":\"insert\"}]","matchedPredicates":"[]","notMatchedBySourcePredicates":"[]"},"engineInfo":"delta-rs:py-1.5.0","clientVersion":"delta-rs.py-1.5.0","readVersion":20,"operationMetrics":{"execution_time_ms":501,"num_output_rows":27010,"num_source_rows":27010,"num_target_files_added":1,"num_target_files_removed":0,"num_target_files_scanned":21,"num_target_files_skipped_during_scan":0,"num_target_rows_copied":0,"num_target_rows_deleted":0,"num_target_rows_inserted":27010,"num_target_rows_updated":0,"rewrite_time_ms":20,"scan_time_ms":449}}}
{"add":{"path":"part-00000-616186cc-1df1-45f6-bbe1-f8ff9983f9fc-c000.snappy.parquet","partitionValues":{},"size":2274281,"modificationTime":1776709776492,"dataChange":true,"stats":"{\"numRecords\":27010,\"minValues\":{\"current_gold\":0,\"total_gold\":0,\"champion_stats_ability_power\":0,\"champion_stats_health_regen\":0,\"champion_stats_attack_damage\":25,\"champion_stats_bonus_magic_pen_percent\":0,\"minions_killed\":0,\"jungle_minions_killed\":0,\"champion_stats_health_max\":530,\"match_id\":\"KR_8154337412\",\"position_x\":25,\"champion_stats_health\":0,\"champion_stats_magic_resist\":-10,\"frame_index\":0,\"champion_stats_armor\":-19,\"time_enemy_spent_controlled\":0,\"champion_stats_armor_pen\":0,\"champion_stats_cc_reduction\":-30,\"champion_stats_magic_pen\":0,\"position_y\":25,\"champion_stats_cooldown_reduction\":0,\"champion_stats_ability_haste\":0,\"xp\":0,\"champion_stats_bonus_armor_pen_percent\":0,\"champion_stats_lifesteal\":0,\"champion_stats_armor_pen_percent\":0,\"participant_id\":1,\"champion_stats_movement_speed\":0,\"level\":1,\"champion_stats_attack_speed\":64,\"champion_stats_magic_pen_percent\":0,\"gold_per_second\":0},\"maxValues\":{\"champion_stats_attack_speed\":533,\"frame_index\":42,\"total_gold\":23866,\"champion_stats_health_max\":7396,\"position_y\":20892,\"champion_stats_cc_reduction\":100,\"time_enemy_spent_controlled\":2031747,\"xp\":29244,\"current_gold\":6440,\"level\":20,\"champion_stats_armor_pen_percent\":54,\"jungle_minions_killed\":260,\"champion_stats_armor_pen\":22,\"champion_stats_health\":7396,\"champion_stats_magic_pen\":48,\"minions_killed\":368,\"champion_stats_movement_speed\":1182,\"champion_stats_ability_haste\":0,\"position_x\":22401,\"champion_stats_armor\":736,\"champion_stats_attack_damage\":837,\"champion_stats_lifesteal\":100,\"champion_stats_bonus_magic_pen_percent\":0,\"champion_stats_cooldown_reduction\":0,\"champion_stats_ability_power\":1069,\"champion_stats_magic_pen_percent\":44,\"champion_stats_bonus_armor_pen_percent\":50,\"champion_stats_health_regen\":7488,\"gold_per_second\":90,\"participant_id\":16,\"champion_stats_magic_resist\":372,\"match_id\":\"KR_8181199435\"},\"nullCount\":{\"current_gold\":0,\"jungle_minions_killed\":0,\"xp\":0,\"position_x\":0,\"total_gold\":0,\"participant_id\":0,\"champion_stats_armor_pen\":0,\"champion_stats_attack_speed\":0,\"champion_stats_health_max\":0,\"champion_stats_health_regen\":0,\"champion_stats_attack_damage\":0,\"champion_stats_lifesteal\":0,\"level\":0,\"champion_stats_bonus_magic_pen_percent\":0,\"champion_stats_bonus_armor_pen_percent\":0,\"champion_stats_health\":0,\"champion_stats_magic_pen_percent\":0,\"frame_index\":0,\"champion_stats_cc_reduction\":0,\"match_id\":0,\"champion_stats_ability_haste\":0,\"position_y\":0,\"champion_stats_ability_power\":0,\"champion_stats_armor\":0,\"champion_stats_armor_pen_percent\":0,\"champion_stats_magic_pen\":0,\"champion_stats_movement_speed\":0,\"champion_stats_cooldown_reduction\":0,\"gold_per_second\":0,\"minions_killed\":0,\"time_enemy_spent_controlled\":0,\"champion_stats_magic_resist\":0}}","tags":null,"baseRowId":null,"defaultRowCommitVersion":null,"clusteringProvider":null}}